ayena/__init__.py
ayena/_openai_scripts.py
ayena/api_requestor.py
ayena/cli.py
ayena/embeddings_utils.py
ayena/error.py
ayena/object_classes.py
ayena/openai_object.py
ayena/openai_response.py
ayena/upload_progress.py
ayena/util.py
ayena/validators.py
ayena/version.py
ayena/wandb_logger.py
ayena/api_resources/__init__.py
ayena/api_resources/audio.py
ayena/api_resources/chat_completion.py
ayena/api_resources/completion.py
ayena/api_resources/customer.py
ayena/api_resources/deployment.py
ayena/api_resources/edit.py
ayena/api_resources/embedding.py
ayena/api_resources/engine.py
ayena/api_resources/error_object.py
ayena/api_resources/file.py
ayena/api_resources/fine_tune.py
ayena/api_resources/fine_tuning.py
ayena/api_resources/image.py
ayena/api_resources/model.py
ayena/api_resources/moderation.py
ayena/api_resources/abstract/__init__.py
ayena/api_resources/abstract/api_resource.py
ayena/api_resources/abstract/createable_api_resource.py
ayena/api_resources/abstract/deletable_api_resource.py
ayena/api_resources/abstract/engine_api_resource.py
ayena/api_resources/abstract/listable_api_resource.py
ayena/api_resources/abstract/nested_resource_class_methods.py
ayena/api_resources/abstract/paginatable_api_resource.py
ayena/api_resources/abstract/updateable_api_resource.py
ayena/api_resources/experimental/__init__.py
ayena/api_resources/experimental/completion_config.py
ayena/datalib/__init__.py
ayena/datalib/common.py
ayena/datalib/numpy_helper.py
ayena/datalib/pandas_helper.py
ayena/tests/__init__.py
ayena/tests/test_api_requestor.py
ayena/tests/test_endpoints.py
ayena/tests/test_exceptions.py
ayena/tests/test_file_cli.py
ayena/tests/test_long_examples_validator.py
ayena/tests/test_url_composition.py
ayena/tests/test_util.py
ayena/tests/asyncio/__init__.py
ayena/tests/asyncio/test_endpoints.py
ayena-1.0.0.dist-info/METADATA
ayena-1.0.0.dist-info/WHEEL
ayena-1.0.0.dist-info/top_level.txt
ayena-1.0.0.dist-info/RECORD
